MANIFEST.in
README.md
setup.py
src/adblockd/__init__.py
src/adblockd/__main__.py
src/adblockd.egg-info/PKG-INFO
src/adblockd.egg-info/SOURCES.txt
src/adblockd.egg-info/dependency_links.txt
src/adblockd.egg-info/entry_points.txt
src/adblockd.egg-info/top_level.txt
test/config-noblock.json
test/config.json