Metadata-Version: 1.0
Name: adblockd
Version: 0.0.4
Summary: Adblock based application
Home-page: https://github.com/rodrigopmatias/adblockd/issues
Author: <generator object read_authores at 0x7f47de566558>
Author-email: <generator object read_emails at 0x7f47de566510>
License: UNKNOWN
Platform: UNKNOWN
